ip/__init__.py
ip/core.py
hanxu-0.1.0.dist-info/LICENSE
hanxu-0.1.0.dist-info/METADATA
hanxu-0.1.0.dist-info/WHEEL
hanxu-0.1.0.dist-info/entry_points.txt
hanxu-0.1.0.dist-info/top_level.txt
hanxu-0.1.0.dist-info/RECORD
