Metadata-Version: 2.1
Name: hanxu
Version: 0.1.0
Summary: A package to get and count IP addresses
Home-page: https://github.com/Xu-Hardy/findyourip
Author: Your Name
Author-email: deep.work.max@gmail.com
License-File: LICENSE
Requires-Dist: click
Requires-Dist: requests
